auto_update/__init__.py
auto_update/update.py
auto_update-0.1.0.dist-info/LICENSE
auto_update-0.1.0.dist-info/METADATA
auto_update-0.1.0.dist-info/WHEEL
auto_update-0.1.0.dist-info/top_level.txt
auto_update-0.1.0.dist-info/RECORD
