Metadata-Version: 2.1
Name: auto-update
Version: 0.1.0
Summary: auto-update is a Python package designed to update Python projects installed on client systems that do not have Git installed. It retrieves the latest release from a specified GitHub repository, compares it with the currently installed version, and updates the project accordingly.
Author-email: Shaik Abdus Samad <shaiksamad.dev@gmail.com>
License: MIT License
Project-URL: Homepage, https://github.com/shaiksamad/auto-update.git
Project-URL: Repository, https://github.com/shaiksamad/auto-update.git
Project-URL: Issues, https://github.com/shaiksamad/auto-update/issues
Keywords: update,auto update scripts,auto update,python script update
Classifier: Intended Audience :: Developers
Classifier: License :: OSI Approved :: MIT License
Classifier: Programming Language :: Python :: 3
Classifier: Programming Language :: Python :: 3.6
Classifier: Programming Language :: Python :: 3.7
Classifier: Programming Language :: Python :: 3.8
Classifier: Programming Language :: Python :: 3.9
Requires-Python: >=3.6
License-File: LICENSE
Requires-Dist: requests
Requires-Dist: diff-parser
